hook_extension/__init__.py
hook_extension/configure_hook.py
hook_extension/describe_hook.py
hook_extension/enable_lambda_hook.py
hook_extension/entry.py
hook_extension/set_default_hook_version.py
cloudformation_cli_hooks_extension-0.2.0.dist-info/LICENSE
cloudformation_cli_hooks_extension-0.2.0.dist-info/METADATA
cloudformation_cli_hooks_extension-0.2.0.dist-info/NOTICE
cloudformation_cli_hooks_extension-0.2.0.dist-info/WHEEL
cloudformation_cli_hooks_extension-0.2.0.dist-info/entry_points.txt
cloudformation_cli_hooks_extension-0.2.0.dist-info/top_level.txt
cloudformation_cli_hooks_extension-0.2.0.dist-info/zip-safe
cloudformation_cli_hooks_extension-0.2.0.dist-info/RECORD
