Metadata-Version: 2.1
Name: cloudformation-cli-hooks-extension
Version: 0.2.0
Summary: Hook extension for the CloudFormation CLI
Home-page: https://github.com/aws-cloudformation/cloudformation-cli-hooks-extension
Author: Amazon Web Services
Author-email: aws-cloudformation-developers@amazon.com
License: Apache License 2.0
Keywords: Amazon Web Services AWS CloudFormation
Platform: UNKNOWN
Classifier: Development Status :: 5 - Production/Stable
Classifier: Environment :: Console
Classifier: Intended Audience :: Developers
Classifier: License :: OSI Approved :: Apache Software License
Classifier: Natural Language :: English
Classifier: Topic :: Software Development :: Build Tools
Classifier: Topic :: Software Development :: Code Generators
Classifier: Operating System :: OS Independent
Classifier: Programming Language :: Python :: 3 :: Only
Classifier: Programming Language :: Python :: 3.6
Classifier: Programming Language :: Python :: 3.7
Classifier: Programming Language :: Python :: 3.8
Classifier: Programming Language :: Python :: 3.9
Classifier: Programming Language :: Python :: 3.10
Classifier: Programming Language :: Python :: 3.11
Requires-Python: >=3.6
Requires-Dist: cloudformation-cli >=0.2.33
